.gitlab-ci.yml
LICENSE
MANIFEST.in
README.md
setup.cfg
setup.py
versioneer.py
bmlx/__init__.py
bmlx/_version.py
bmlx/alarm.py
bmlx/alarm_test.py
bmlx/bmlx.yml
bmlx/bmlx_ini.py
bmlx/config.py
bmlx/config_test.py
bmlx/context.py
bmlx/context_test.py
bmlx/dependencies.py
bmlx/project_spec.py
bmlx/project_spec_test.py
bmlx.egg-info/PKG-INFO
bmlx.egg-info/SOURCES.txt
bmlx.egg-info/dependency_links.txt
bmlx.egg-info/entry_points.txt
bmlx.egg-info/namespace_packages.txt
bmlx.egg-info/requires.txt
bmlx.egg-info/top_level.txt
bmlx/cli/__init__.py
bmlx/cli/cli_exception.py
bmlx/cli/constants.py
bmlx/cli/context.py
bmlx/cli/handlers/__init__.py
bmlx/cli/handlers/artifact.py
bmlx/cli/handlers/component.py
bmlx/cli/handlers/component_execution.py
bmlx/cli/handlers/execution.py
bmlx/cli/handlers/experiment.py
bmlx/cli/handlers/graph.py
bmlx/cli/handlers/login.py
bmlx/cli/handlers/pipeline.py
bmlx/cli/handlers/pipeline_version.py
bmlx/cli/handlers/plugin.py
bmlx/cli/handlers/project.py
bmlx/cli/handlers/utils.py
bmlx/cli/runtime/__init__.py
bmlx/cli/runtime/component.py
bmlx/cli/runtime/main.py
bmlx/cli/runtime/pipeline.py
bmlx/cli/ui/__init__.py
bmlx/cli/ui/main.py
bmlx/cli/ui/project.py
bmlx/execution/__init__.py
bmlx/execution/driver.py
bmlx/execution/driver_test.py
bmlx/execution/execution.py
bmlx/execution/execution_test.py
bmlx/execution/launcher.py
bmlx/execution/launcher_test.py
bmlx/execution/multiprocess_runner.py
bmlx/execution/runner.py
bmlx/execution/runner_test.py
bmlx/execution/bmlxflow/__init__.py
bmlx/execution/bmlxflow/argo_node.py
bmlx/execution/bmlxflow/bmlxflow_runner.py
bmlx/execution/bmlxflow/workflow.py
bmlx/execution/bmlxflow/workflow_test.py
bmlx/flow/__init__.py
bmlx/flow/artifact.py
bmlx/flow/artifact_test.py
bmlx/flow/channel.py
bmlx/flow/channel_test.py
bmlx/flow/component.py
bmlx/flow/component_test.py
bmlx/flow/driver_spec.py
bmlx/flow/executor_spec.py
bmlx/flow/hook.py
bmlx/flow/node.py
bmlx/flow/pipeline.py
bmlx/flow/pipeline_test.py
bmlx/fs/__init__.py
bmlx/fs/ceph.py
bmlx/fs/ceph_test.py
bmlx/fs/file_system.py
bmlx/fs/hdfs.py
bmlx/fs/hdfs_test.py
bmlx/metadata/__init__.py
bmlx/metadata/bmlxflow_store.py
bmlx/metadata/bmlxflow_store_test.py
